setup.cfg
setup.py
restaurant_service_flask.egg-info/PKG-INFO
restaurant_service_flask.egg-info/SOURCES.txt
restaurant_service_flask.egg-info/dependency_links.txt
restaurant_service_flask.egg-info/top_level.txt
service/__init__.py
service/controllers/__init__.py
service/controllers/application_controller.py
service/models/__init__.py
service/models/menu_item.py
service/repositories/__init__.py
service/repositories/menu_repository.py
tests/__init__.py