Metadata-Version: 1.0
Name: restaurant-service-flask
Version: 0.1.0
Summary: Restaurant Service - Flask Version
Home-page: https://github.com/Kalimaha/restaurant-service-flask
Author: Guido Barbaglia
Author-email: guido.barbaglia@gmail.com
License: LICENSE
Platform: UNKNOWN
